{
    "frvb1.png": {
        "contentType": "image/png", 
        "content_son": {
            "category": "asset", 
            "course": "MECH21", 
            "name": "frvb1.png", 
            "org": "NITK", 
            "revision": null, 
            "run": "anytime", 
            "tag": "c4x"
        }, 
        "displayname": "frvb1.png", 
        "filename": "asset-v1:NITK+MECH21+anytime+type@asset+block@frvb1.png", 
        "import_path": null, 
        "locked": false, 
        "thumbnail_location": [
            "c4x", 
            "NITK", 
            "MECH21", 
            "thumbnail", 
            "frvb1-png.jpg", 
            null
        ]
    }
}